ethextended/__init__.py
ethextended/account.py
ethextended/errors.py
ethextended/gas.py
ethextended/identicon.py
ethextended/utils.py
ethextended-0.2.1.dist-info/LICENSE
ethextended-0.2.1.dist-info/METADATA
ethextended-0.2.1.dist-info/WHEEL
ethextended-0.2.1.dist-info/top_level.txt
ethextended-0.2.1.dist-info/RECORD
