Metadata-Version: 2.1
Name: ethextended
Version: 0.2.1
Summary: Library with extra tools for ethereum, provided by Etherscan, Eth Gas Station, etc.
Home-page: https://github.com/AlexSSD7/ethextended
Author: AlexSSD7
Author-email: UNKNOWN
License: MIT
Platform: UNKNOWN
Requires-Dist: bs4
Requires-Dist: requests
Requires-Dist: lxml
Requires-Dist: pysha3
